Metadata-Version: 2.1
Name: gitstat
Version: 0.4.4
Summary: UNKNOWN
Home-page: UNKNOWN
License: UNKNOWN
Platform: UNKNOWN
